{"map":[[0,[0,{"color":"blue","shape":"square"}]]],"players":[{"score":0,"name":"A","tile*":[{"color":"blue","shape":"circle"},{"color":"red","shape":"circle"},{"color":"green","shape":"star"},{"color":"orange","shape":"circle"},{"color":"yellow","shape":"diamond"},{"color":"purple","shape":"circle"}]},{"score":2,"name":"B","tile*":[{"color":"orange","shape":"diamond"},{"color":"red","shape":"circle"},{"color":"blue","shape":"square"},{"color":"green","shape":"diamond"},{"color":"blue","shape":"8star"},{"color":"green","shape":"star"}]},{"score":0,"name":"C","tile*":[{"color":"yellow","shape":"star"},{"color":"green","shape":"diamond"},{"color":"purple","shape":"circle"},{"color":"blue","shape":"8star"},{"color":"purple","shape":"clover"},{"color":"red","shape":"8star"}]},{"score":0,"name":"D","tile*":[{"color":"green","shape":"8star"},{"color":"blue","shape":"circle"},{"color":"yellow","shape":"square"},{"color":"orange","shape":"diamond"},{"color":"yellow","shape":"clover"},{"color":"red","shape":"clover"}]}],"tile*":[{"color":"green","shape":"square"},{"color":"yellow","shape":"square"},{"color":"blue","shape":"square"},{"color":"green","shape":"8star"},{"color":"red","shape":"square"},{"color":"green","shape":"8star"}]}
[["A","dag"],["B","ldasg"],["C","dag","take-turn",1],["D","dag"]]
