{"map":[[0,[0,{"color":"red","shape":"circle"}],[1,{"color":"red","shape":"square"}],[2,{"color":"red","shape":"star"}]],[1,[0,{"color":"blue","shape":"circle"}],[1,{"color":"blue","shape":"square"}],[2,{"color":"blue","shape":"star"}]],[2,[0,{"color":"green","shape":"circle"}],[1,{"color":"green","shape":"square"}],[2,{"color":"green","shape":"star"}]]],"players":[{"score":0,"tile*":[{"color":"yellow","shape":"circle"}]}],"tile*":1077}
[{"1tile":{"color":"yellow","shape":"circle"},"coordinate":{"column":0,"row":3}}]

